setup.py
mathplot/Binomialdistribution.py
mathplot/Gaussiandistribution.py
mathplot/Generaldistribution.py
mathplot/__init__.py
mathplot.egg-info/PKG-INFO
mathplot.egg-info/SOURCES.txt
mathplot.egg-info/dependency_links.txt
mathplot.egg-info/not-zip-safe
mathplot.egg-info/top_level.txt