Metadata-Version: 1.0
Name: mathplot
Version: 0.1
Summary: Gaussian and Binomial distributions
Home-page: UNKNOWN
Author: Manoj Aryal
Author-email: UNKNOWN
License: UNKNOWN
Platform: UNKNOWN
